Workbook

Sheet Invoice
A1: GUANGZHOU AC SKINCARE PACKAGING CO.,LTD
A2: Room 1002, Shuixi Fuye 1st Street, Huangpu District, Guangzhou, CN Phone: +8618688407515 Emai.l: ANNE@SKINCAREPKG.COM
A4: INVOICE
A5: TO: | B5: IZIL COSMETICS INDUSTRIES, LLC PLOT NO:214050145,UNIT NO:2 BUILDING #21405,SALIHIA 214 RAS AL KHAIMAH. UAE. SHARLET ROBERT CASTELINO SHARLET.CASTELINO@IZILBEAUTY.COM +971555014285 | G5: Invoice No:PI-AC26012301-1 Payment Terms: T/T Before Shipment,30DAY(S); Country of origin - China DATE: 2026/5/19
A7: 唛号与号码 Marks & No. | D7: 品名 Product | E7: 数量 Quantities | F7: 箱数 Cartons | G7: 单价 Unit Price EXW Factory | H7: 总值 Amount EXW Factory
A8: AC26012301 | D8: plastic bottle HS code: 3923300000 | E8: =7776+330 -> 8106 | F8: 19 | G8: 0.304 | H8: =G8*E8 -> 2464.224
D9: Cosmetic tube HS CODE 3923900000 | E9: 9360 | F9: 39 | G9: 0.4364 | H9: =G9*E9 -> 4084.704
D10: TOTAL | H10: =SUM(H8:H9) -> 6548.928
D11: FREE OF CHARGE QUANTITY | H11: 231.71
D12: SUBTOTAL AMOUNT | H12: =H10-H11 -> 6317.218

Sheet Packing list
A1: GUANGZHOU AC SKINCARE PACKAGING CO.,LTD Room 1002, Shuixi Fuye 1st Street, Huangpu District, Guangzhou, CN Phone: +8618688407515 Emai.l: ANNE@SKINCAREPKG.COM
A3: PACKING LIST
A4: TO: | B4: IZIL COSMETICS INDUSTRIES, LLC PLOT NO:214050145,UNIT NO:2 BUILDING #21405,SALIHIA 214 RAS AL KHAIMAH. UAE. SHARLET ROBERT CASTELINO SHARLET.CASTELINO@IZILBEAUTY.COM +971555014285 | J4: Invoice No:PI-AC26012301-1 Country of origin - China DATE: 2026/5/19
D7: CARTON | K7: TOTAL
A8: NO | B8: PRODUCTION NAME 产品名 | C8: QTY 订单数量 | D8: QTY/CTN 个/箱 | E8: CARTON. SIZE CM 纸箱尺寸 | H8: CBM 体积 | I8: N.W. 净重 | J8: G.W 毛重 | K8: CARTON 总箱数 | L8: N.W. 总净重 | M8: G.W. 总毛重 | N8: CBM 总体积
A9: 1 | B9: =Invoice!D8 -> plastic bottle HS code: 3923300000 | C9: =Invoice!E8 -> 8106 | D9: 240 | E9: 48 | F9: 33 | G9: 46 | H9: =0.48*0.33*0.46 -> 0.072864 | I9: 13 | J9: 14 | K9: =Invoice!F8 -> 19 | L9: 161.57 | M9: =198+29.5 -> 227.5 | N9: 2.5
A10: 2 | B10: =Invoice!D9 -> Cosmetic tube HS CODE 3923900000 | C10: =Invoice!E9 -> 9360 | D10: =Invoice!F9 -> 39 | E10: =Invoice!G9 -> 0.4364 | F10: =Invoice!H9 -> 4084.704 | G10: =Invoice!I9 -> 0 | H10: =Invoice!J9 -> 0 | I10: =Invoice!K9 -> 0 | J10: =Invoice!L9 -> 0 | K10: =Invoice!F9 -> 39 | L10: 18 | M10: 318 | N10: 4.689
A11: TOTAL | K11: =SUM(K9:K10) -> 58 | L11: =SUM(L9:L10) -> 179.57 | M11: =SUM(M9:M10) -> 545.5 | N11: =SUM(N9:N10) -> 7.189

Sheet Contract
A1: GUANGZHOU AC SKINCARE PACKAGING CO.,LTD RM 216, No. 10 Longdong Street, Tianhe District, Guangzhou, CN Phone: +8618688407515 Emai.l: ANNE@SKINCAREPKG.COM
A3: 售 货 合 同
A4: SALES CONTRACT
A5: 下列签字双方同意按以下条款达成交易： | D5: PI NO：
A6: The undersigned Sellers and Buyers have agreed to close the following transactions | D6: DATE：
A7: according to the terms andconditions stipulated below :
A8: 品名及规格 COMMODITY AND SPECIFICATION | B8: 数量 QUANTITY | C8: 单位 DUAL | D8: 单价 UNIT PRICE | E8: 金额 AMOUNT
E15: =SUM(E9:E14) -> 0
A16: (5)装运期限: | C16: (6)装运数量允许有 %在增减
A17: Shipment: | C17: Shipment quantity % more or less allowed
A18: (7)装运口岸: | C18: (8)目的港:
A19: Port of loading: | C19: Port of Destination：
A20: (9)付款方式 PAYMENT: 在装柜之前开到卖方100%保兑的、不可撤销的、即期付款信用证，须注明装运日期后, 十五天内在中国议付有效，允许转船及分批装运，并注明有关合同号码，议付金额允许有5%的增减。幅度以实际装运数量为准。 By 100% confirmed. Irrevocable L/C to be opened to be seller before and to be available by sight draft,to remain valid for negotiation in China untill the 15th days after the Date of Shipment,allowing transhipmentand partial shipmetns, mentioning the relative contract number and the negotiated amount %more or less allowable with subject to the actual shipped quanlity.
A22: (10)保 险: 投保 由卖方按发票金额110%投保。
A23: INSURANCE : Covering Risks for 110% of invoice value to be effected by the Seller.
A26: 买方签字 | C26: 卖方签字
A27: The Buyer's Signature | C27: The Seller's Signature
