Workbook

Sheet Invoice
A1: GUANGZHOU AC SKINCARE PACKAGING CO.,LTD
A2: RM 1002, Shuixi Fuye 1st Street, Huangpu District, Guangzhou, CN Phone: +8618688407515 Emai.l: ANNE@SKINCAREPKG.COM
A3: COMMERCIAL INVOICE
A4: TO: | B4: Company: Midvision Pvt Ltd Name: Mr Rishi Phone: 0049054018363-413 Address: SCO 41, Chotti Baradari Part 2, Opposite PIMS Hospital, Jalandhar, Punjab 144001，India | G4: Invoice No: PI-AC250722 Payment Terms: T/T Before Shipment,30DAY(S); Date: 2026/06/05
A5: 唛号与号码 Marks & No. | D5: 品名 Product | E5: 数量 Quantities | F5: 箱数 Cartons | G5: 单价 Unit Price EXW Factory USD | H5: 总值 Amount EXW Factory USD
A6: AC250722 | D6: ='[2]Packing list'!B8 -> Plastic bottle 塑料瓶 | E6: 16480 | F6: 58 | G6: 0.2 | H6: =G6*E6 -> 3296
D7: Plastic pump塑料泵头 | E7: 13088 | F7: 43 | G7: 0.3 | H7: =G7*E7 -> 3926.4
D8: ='[2]Packing list'!B10 -> Plastic cover 塑料外盖 | E8: 3168 | F8: 1 | G8: 0.2612 | H8: =G8*E8 -> 827.4816
H9: =SUM(H6:H8) -> 8049.8816

Sheet Packing list
A1: GUANGZHOU AC SKINCARE PACKAGING CO.,LTD RM 1002, Shuixi Fuye 1st Street, Huangpu District, Guangzhou, CN Phone: +8618688407515 Emai.l: ANNE@SKINCAREPKG.COM
A2: PACKING LIST
A3: TO: | B3: AU NATUREL BEAUTY PRIVATE LIMITED Address: 7KM MILE STONE, KAIZEN DAIRY FOODWORKS PRIVATE LIMITED, ATELI KANINA ROAD, MAHASAR, MAHENDRAGARH, HARYANA - 123021 GST: 06AAVCA8783E1Z3 IEC: AAVCA8783E Email: advay@neudeskin.com neudeskincare@gmail.com | J3: Invoice: PI-AC250722 Date: 2026/06/05
D6: CARTON | K6: TOTAL
A7: NO | B7: PRODUCTION NAME 产品名 | C7: QTY 订单数量 | D7: QTY/CTN 个/箱 | E7: CARTON. SIZE CM 纸箱尺寸 | H7: CBM 体积 | I7: N.W. 净重 | J7: G.W 毛重 | K7: CARTON 总箱数 | L7: N.W. 总净重 | M7: G.W. 总毛重 | N7: CBM 总体积
A8: 1 | B8: Plastic bottle 塑料瓶 | C8: =Invoice!E6 -> 16480 | K8: =Invoice!F6 -> 58 | L8: =M8-K8 -> 489.2 | M8: 547.2 | N8: 6.6
A9: 2 | B9: Plastic pump塑料泵头 | C9: =Invoice!E7 -> 13088 | K9: =Invoice!F7 -> 43 | L9: =M9-K9 -> 377 | M9: 420 | N9: 3.1
A10: 3 | B10: Plastic cover 塑料外盖 | C10: =Invoice!E8 -> 3168 | K10: =Invoice!F8 -> 1 | L10: =M10-K10 -> 11.6 | M10: 12.6 | N10: 0.17
A11: TOTAL | K11: =SUM(K8:K10) -> 102 | L11: =SUM(L8:L10) -> 877.8 | M11: =SUM(M8:M10) -> 979.8 | N11: =SUM(N8:N10) -> 9.87
A13: TOTAL CARTONS:
A14: TOTAL N.W.:
A15: TOTAL G.W.:
A16: TOTAL VOLUME
A17: SHIPPING MARK:

Sheet Contract
A1: GUANGZHOU AC SKINCARE PACKAGING CO.,LTD RM 1002, Shuixi Fuye 1st Street, Huangpu District, Guangzhou, CN Phone: +8618688407515 Emai.l: ANNE@SKINCAREPKG.COM
A3: 售 货 合 同
A4: SALES CONTRACT
A5: 下列签字双方同意按以下条款达成交易： | D5: PI NO：
A6: The undersigned Sellers and Buyers have agreed to close the following transactions | D6: DATE：
A7: according to the terms andconditions stipulated below :
A8: 品名及规格 COMMODITY AND SPECIFICATION | B8: 数量 QUANTITY | C8: 单位 DUAL | D8: 单价 UNIT PRICE | E8: 金额 AMOUNT
E15: =SUM(E9:E14) -> 0
A16: (5)装运期限: | C16: (6)装运数量允许有 %在增减
A17: Shipment: | C17: Shipment quantity % more or less allowed
A18: (7)装运口岸: | C18: (8)目的港:
A19: Port of loading: | C19: Port of Destination：
A20: (9)付款方式 PAYMENT: 在装柜之前开到卖方100%保兑的、不可撤销的、即期付款信用证，须注明装运日期后, 十五天内在中国议付有效，允许转船及分批装运，并注明有关合同号码，议付金额允许有5%的增减。幅度以实际装运数量为准。 By 100% confirmed. Irrevocable L/C to be opened to be seller before and to be available by sight draft,to remain valid for negotiation in China untill the 15th days after the Date of Shipment,allowing transhipmentand partial shipmetns, mentioning the relative contract number and the negotiated amount %more or less allowable with subject to the actual shipped quanlity.
A22: (10)保 险: 投保 由卖方按发票金额110%投保。
A23: INSURANCE : Covering Risks for 110% of invoice value to be effected by the Seller.
A26: 买方签字 | C26: 卖方签字
A27: The Buyer's Signature | C27: The Seller's Signature

Sheet 报关单
A1: 中华人民共和国海关出口货物报关单
A2: 预录入编号： 海关编号： 页码/页数： | J2: =([1]输入表格!B28) -> 进仓编号：
A3: 境内发货人 | C3: 出境关别 | E3: 出口日期 | G3: 申报日期 | J3: 备案号
A4: =([1]输入表格!B11) -> 宁波奉化广翰进出口有限公司91330283MABPU9X91B | C4: =([1]输入表格!B16) -> 0
A5: 境外收货人 | C5: 运输方式 | E5: 运输工具名称及航次号 | G5: 提运单号
C6: =([1]输入表格!B29) -> 航空运输 | E6: =([1]输入表格!B25) -> 0 | G6: =([1]输入表格!B26) -> 0
A7: 生产销售单位 | C7: 监管方式 | E7: 征免性质 | G7: 许可证号
A8: =([1]输入表格!B14) -> 宁波奉化广翰进出口有限公司91330283MABPU9X91B | C8: 一般贸易 | E8: 一般征税
A9: 合同协议号 | B9: =[1]输入表格!B17 -> 0 | C9: 贸易国（地区） | E9: 运抵国（地区） | G9: 指运港 | J9: 离境口岸
A10: 运输包装种类 | B10: 其他包装种类及对应数量 | C10: 件数 | D10: 毛重（千克） | E10: 净重(千克) | F10: 成交方式 | G10: 运费 | J10: 保费 | L10: 杂费
A11: =([1]输入表格!F9) -> 纸箱 | C11: =1 -> 1 | D11: 67.5 | E11: 65 | F11: FOB | G11: 0 | J11: 0 | L11: 0
A12: 随附单证及编号
A13: 标记唛码及备注
A14: =([1]输入表格!B30) -> N/M
A15: 集装箱对应商品关系,集装箱货重:
A17: 项号 商品编号 商品名称及规格型号 数量及单位 单价/总价/币制 原产国(地区) 最终目的国（地区） 境内货源地 征免
A18: 1
A19: 2
A20: 3
A21: 4
A22: 5
A23: 6
B24: 0:品牌类型：0|1:出口享惠情况:0|2:用途：路由器金属配件|3:材质：铝|4:品牌：无|5:规格或型号：无|6:GTIN：无|7:CAS：无
F30: TOTAL: | G30: =SUM(G18:G23) -> 0
A31: 报关人员 报关人员证号 电话 兹申明对以上内容承担如实申报、依法纳税之法律责任 申报单位 申报单位（签章） | J31: 海关批注及签章
